README.md
setup.py
find_domains/__init__.py
find_domains/util.py
find_domains.egg-info/PKG-INFO
find_domains.egg-info/SOURCES.txt
find_domains.egg-info/dependency_links.txt
find_domains.egg-info/requires.txt
find_domains.egg-info/top_level.txt
test/test_find_domains.py